{
  "hash": "fbfe963d",
  "configHash": "794b5e21",
  "lockfileHash": "d334b763",
  "browserHash": "26854144",
  "optimized": {
    "react": {
      "src": "../../node_modules/react/index.js",
      "file": "react.js",
      "fileHash": "6738161a",
      "needsInterop": true
    },
    "react-dom/client": {
      "src": "../../node_modules/react-dom/client.js",
      "file": "react-dom_client.js",
      "fileHash": "5d193375",
      "needsInterop": true
    }
  },
  "chunks": {
    "chunk-KHA5YKM3": {
      "file": "chunk-KHA5YKM3.js"
    }
  }
}